pybiomedlink/__init__.py
pybiomedlink/linker.py
pybiomedlink/exp_scripts/bert_emb.py
pybiomedlink/exp_scripts/bm25.py
pybiomedlink/exp_scripts/edit_dist.py
pybiomedlink-0.2.1.dist-info/licenses/LICENSE
pybiomedlink-0.2.1.dist-info/METADATA
pybiomedlink-0.2.1.dist-info/WHEEL
pybiomedlink-0.2.1.dist-info/top_level.txt
pybiomedlink-0.2.1.dist-info/RECORD
