Metadata-Version: 2.4
Name: pyBioMedLink
Version: 0.2.1
Summary: pyBioMedLink for Bio-Medical Term Linking.
Author: Jiaying Lu
Maintainer-email: jiaying.lu@emory.edu
License: Apache-2.0
Project-URL: Repository, https://github.com/GAIN-Lab/pyBioMedLink
Classifier: Programming Language :: Python :: 3
Classifier: License :: OSI Approved :: Apache Software License
Classifier: Operating System :: OS Independent
Requires-Python: >=3.11
License-File: LICENSE
Requires-Dist: accelerate>=1.9.0
Requires-Dist: rank-bm25>=0.2.2
Requires-Dist: torch>=2.7.1
Requires-Dist: transformers>=4.53.2
Dynamic: license-file
